CHANGES.md
LICENSE.md
MANIFEST.in
README.md
VERSION
pyproject.toml
requirements-docs.txt
requirements-tests.txt
requirements.txt
setup.cfg
setup.py
bin/radical-gtod-version
examples/00_gtod.py
src/radical.gtod.egg-info/PKG-INFO
src/radical.gtod.egg-info/SOURCES.txt
src/radical.gtod.egg-info/dependency_links.txt
src/radical.gtod.egg-info/not-zip-safe
src/radical.gtod.egg-info/requires.txt
src/radical.gtod.egg-info/top_level.txt
src/radical/gtod/VERSION
src/radical/gtod/__init__.py
src/radical/gtod/gtod.c
src/radical/gtod/radical-gtod