Metadata-Version: 2.4
Name: radical.gtod
Version: 1.103.0
Summary: returns seconds since epoch in subsecond resolution.
Home-page: http://radical-cybertools.github.io/radical.gtod/
Author: RADICAL Group at Rutgers University
Author-email: radical@rutgers.edu
Maintainer: The RADICAL Group
Maintainer-email: radical@rutgers.edu
License: GPL3
Project-URL: Documentation, https://radicalgtod.readthedocs.io/en/latest/
Project-URL: Source, https://github.com/radical-cybertools/radical.gtod/
Project-URL: Issues, https://github.com/radical-cybertools/radical.gtod/issues
Keywords: radical,cybertools,utilities,gtod,time,epoch
Classifier: Development Status :: 5 - Production/Stable
Classifier: Intended Audience :: Developers
Classifier: Environment :: Console
Classifier: License :: OSI Approved :: GNU General Public License v3 (GPLv3)
Classifier: Programming Language :: Python
Classifier: Programming Language :: Python :: 3
Classifier: Programming Language :: Python :: 3.8
Classifier: Topic :: Utilities
Classifier: Topic :: System :: Distributed Computing
Classifier: Topic :: Scientific/Engineering
Classifier: Operating System :: POSIX
Classifier: Operating System :: Unix
Requires-Python: >=3.8
License-File: LICENSE.md
Requires-Dist: radical.utils<1.110,>=1.100.0
Dynamic: author
Dynamic: author-email
Dynamic: classifier
Dynamic: description
Dynamic: description-content-type
Dynamic: home-page
Dynamic: keywords
Dynamic: license
Dynamic: license-file
Dynamic: maintainer
Dynamic: maintainer-email
Dynamic: project-url
Dynamic: requires-dist
Dynamic: requires-python
Dynamic: summary
